buf/__init__.py
buf/validate/__init__.py
buf/validate/expression_pb2.py
buf/validate/expression_pb2.pyi
buf/validate/expression_pb2_grpc.py
buf/validate/validate_pb2.py
buf/validate/validate_pb2.pyi
buf/validate/validate_pb2_grpc.py
buf/validate/priv/__init__.py
buf/validate/priv/private_pb2.py
buf/validate/priv/private_pb2.pyi
buf/validate/priv/private_pb2_grpc.py
scalekit/__init__.py
scalekit/auth.py
scalekit/client.py
scalekit/connected_accounts.py
scalekit/connection.py
scalekit/core.py
scalekit/directory.py
scalekit/domain.py
scalekit/m2m_client.py
scalekit/mcp.py
scalekit/organization.py
scalekit/passwordless.py
scalekit/permissions.py
scalekit/role.py
scalekit/sessions.py
scalekit/tools.py
scalekit/users.py
scalekit/webauthn.py
scalekit/actions/__init__.py
scalekit/actions/actions.py
scalekit/actions/modifier.py
scalekit/actions/types.py
scalekit/actions/frameworks/__init__.py
scalekit/actions/frameworks/google_adk.py
scalekit/actions/frameworks/langchain.py
scalekit/actions/frameworks/util.py
scalekit/actions/frameworks/types/__init__.py
scalekit/actions/frameworks/types/google_adk_tool.py
scalekit/actions/models/__init__.py
scalekit/actions/models/mcp_config.py
scalekit/actions/models/mcp_instance.py
scalekit/actions/models/tool_input_output.py
scalekit/actions/models/tool_mapping.py
scalekit/actions/models/requests/__init__.py
scalekit/actions/models/requests/create_connected_account_request.py
scalekit/actions/models/requests/mcp_request.py
scalekit/actions/models/requests/tool_request.py
scalekit/actions/models/requests/update_connected_account_request.py
scalekit/actions/models/responses/__init__.py
scalekit/actions/models/responses/create_connected_account_response.py
scalekit/actions/models/responses/create_mcp_config_response.py
scalekit/actions/models/responses/create_mcp_response.py
scalekit/actions/models/responses/delete_connected_account_response.py
scalekit/actions/models/responses/delete_mcp_config_response.py
scalekit_sdk_python-2.4.15.dist-info/licenses/LICENSE
scalekit_sdk_python-2.4.15.dist-info/METADATA
scalekit_sdk_python-2.4.15.dist-info/WHEEL
scalekit_sdk_python-2.4.15.dist-info/top_level.txt
scalekit_sdk_python-2.4.15.dist-info/RECORD
