Metadata-Version: 2.4
Name: scalekit-sdk-python
Version: 2.4.15
Summary: Scalekit official Python SDK
Home-page: https://github.com/scalekit-inc/scalekit-sdk-python
Author: Team Scalekit
Author-email: support@scalekit.com
License: MIT
Classifier: Programming Language :: Python :: 3
Classifier: License :: OSI Approved :: MIT License
Classifier: Operating System :: OS Independent
License-File: LICENSE
Requires-Dist: grpcio>=1.64.1
Requires-Dist: protobuf<=6.32.0,>=5.26.1
Requires-Dist: google>=3.0
Requires-Dist: requests>=2.32.3
Requires-Dist: PyJWT<2.11,>=2.8
Requires-Dist: cffi>=1.15.1
Requires-Dist: cryptography==45.0.6
Requires-Dist: setuptools<81.0,>=78.1.1
Requires-Dist: grpcio-status<1.67,>=1.64
Requires-Dist: protoc-gen-openapiv2>=0.0.1
Requires-Dist: googleapis-common-protos<1.66.0,>=1.56.1
Requires-Dist: deprecation>=2.1.0
Requires-Dist: python-dotenv~=1.1.1
Requires-Dist: Faker~=25.8.0
Requires-Dist: pydantic>=2.10.6
Requires-Dist: mcp>=1.23.0
Dynamic: author
Dynamic: author-email
Dynamic: classifier
Dynamic: description
Dynamic: description-content-type
Dynamic: home-page
Dynamic: license
Dynamic: license-file
Dynamic: requires-dist
Dynamic: summary
